quickshow/__init__.py
quickshow/cluster.py
quickshow/eval_clf_model.py
quickshow/reduce_dim.py
quickshow/utils.py
quickshow-0.1.14.dist-info/LICENSE
quickshow-0.1.14.dist-info/METADATA
quickshow-0.1.14.dist-info/WHEEL
quickshow-0.1.14.dist-info/top_level.txt
quickshow-0.1.14.dist-info/RECORD
