Metadata-Version: 2.1
Name: quickshow
Version: 0.1.14
Summary: Quick-Show provides simply but powerful insight plots
Home-page: https://github.com/DSDanielPark/quick-show
Author: parkminwoo
Author-email: parkminwoo1991@gmail.com
License: UNKNOWN
Keywords: Visuallization,Matplotlib,Plotting,Data Science
Platform: UNKNOWN
Classifier: Development Status :: 2 - Pre-Alpha
Classifier: Intended Audience :: Developers
Classifier: Natural Language :: English
Classifier: Programming Language :: Python
Classifier: Programming Language :: Python :: 3.6
Classifier: Programming Language :: Python :: 3.7
Classifier: Programming Language :: Python :: 3.8
Classifier: Programming Language :: Python :: 3.9
Classifier: Programming Language :: Python :: Implementation :: CPython
Requires-Python: >=3.6
License-File: LICENSE
Requires-Dist: seaborn
Requires-Dist: numpy
Requires-Dist: pandas
Requires-Dist: matplotlib
Requires-Dist: scikit-learn
